[{"날짜": "20160301", "일일연속극(우리집꿀단지)": "27.3", "KBS9시뉴스": "19.3", "일일드라마(천상의약속)": "18.0", "창사특별기획(육룡이나르샤)": "16.4", "일일특별기획(아름다운당신)": "14.1", "MBC아침드라마(내일도승리)": "13.8", "월화특별기획(화려한유혹)": "12.8", "KBS뉴스7": "12.6", "리얼스토리눈": "11.5", "이웃집찰스": "11.3", "시청자칼럼우리사는세상": "10.9", "6시내고향": "10.9", "아침일일연속극(내사위의여자)": "10.3", "TV소설(내마음의꽃비)": "9.7", "일일드라마(마녀의성)": "9.6", "2TV생생정보": "8.6", "아침마당": "8.5", "KBS뉴스(09:30)": "8.3", "일일연속극(최고의연인)": "8.3", "인간극장": "8.3"}, {"날짜": "20160302", "일일연속극(우리집꿀단지)": "26.5", "공사창립특별기획(태양의후예)": "23.4", "KBS9시뉴스": "18.1", "일일드라마(천상의약속)": "17.9", "일일특별기획(아름다운당신)": "13.8", "MBC아침드라마(내일도승리)": "13.6", "아침일일연속극(내사위의여자)": "11.3", "리얼스토리눈": "10.8", "KBS뉴스7": "10.6", "인간극장": "10.3", "일일드라마(마녀의성)": "9.9", "6시내고향": "9.4", "TV소설(내마음의꽃비)": "9.2", "KBS뉴스광장2부": "9.0", "아침마당": "8.7", "시청자칼럼우리사는세상": "8.7", "황금어장라디오스타": "8.6", "일일연속극(최고의연인)": "8.6", "사람과사람들": "7.6", "KBS뉴스(09:30)": "7.6"}, {"날짜": "20160303", "일일연속극(우리집꿀단지)": "26.8", "공사창립특별기획(태양의후예)": "24.1", "KBS9시뉴스": "18.1", "일일드라마(천상의약속)": "16.8", "MBC아침드라마(내일도승리)": "14.2", "일일특별기획(아름다운당신)": "12.7", "KBS뉴스7": "11.2", "아침일일연속극(내사위의여자)": "10.9", "6시내고향": "10.7", "한국인의밥상": "10.5", "순간포착": "10.2", "인간극장": "9.7", "KBS뉴스광장2부": "9.5", "일일드라마(마녀의성)": "9.0", "일일연속극(최고의연인)": "8.9", "TV소설(내마음의꽃비)": "8.6", "자기야": "7.9", "아침마당": "7.8", "KBS뉴스(09:30)": "7.6", "리얼스토리눈": "7.3"}, {"날짜": "20160304", "일일연속극(우리집꿀단지)": "24.7", "KBS9시뉴스": "17.2", "MBC아침드라마(내일도승리)": "14.0", "정글의법칙샵TONGA": "13.5", "KBS뉴스7": "12.6", "일일특별기획(아름다운당신)": "11.1", "아침일일연속극(내사위의여자)": "11.0", "6시내고향": "10.9", "똑똑한소비자리포트": "10.1", "인간극장": "10.0", "아침마당": "9.4", "일일드라마(마녀의성)": "9.4", "일일연속극(최고의연인)": "9.3", "궁금한이야기Y": "9.3", "KBS뉴스광장2부": "9.1", "TV소설(내마음의꽃비)": "8.7", "나혼자산다": "7.9", "MBC뉴스데스크": "7.4", "KBS뉴스(09:30)": "7.3", "SBS8뉴스": "6.7"}, {"날짜": "20160305", "주말연속극(아이가다섯)": "23.6", "주말특별기획(결혼계약)": "17.2", "주말드라마(가화만사성)": "13.3", "무한도전": "13.0", "KBS9시뉴스": "12.9", "대하드라마(장영실)": "11.5", "공사창립특별기획(태양의후예<재>)": "10.4", "시니어토크쇼황금연못": "10.3", "걸어서세계속으로": "9.5", "불후의명곡": "9.4", "특별기획(미세스캅2)": "9.2", "남북의창": "9.1", "그것이알고싶다": "9.1", "KBS뉴스(09:30)": "8.6", "다큐공감": "8.5", "슈퍼맨이돌아왔다스페셜": "8.0", "토요일이좋다2부(백종원의3대천왕)": "7.9", "주말드라마(그래그런거야)": "7.7", "SBS8뉴스": "7.6", "KBS뉴스(19:00)": "7.6"}, {"날짜": "20160306", "주말연속극(아이가다섯)": "27.7", "주말특별기획(결혼계약)": "18.0", "주말드라마(가화만사성)": "15.7", "KBS9시뉴스": "14.5", "일밤(미스터리음악쇼복면가왕,리얼입대프로젝트진짜사나이2)": "13.6", "해피선데이": "12.6", "전국노래자랑": "12.2", "대하드라마(장영실)": "11.8", "개그콘서트": "11.2", "일요일이좋다(런닝맨,서바이벌오디션K팝스타5)": "9.4", "주말드라마(그래그런거야)": "9.3", "특별기획(미세스캅2)": "9.3", "TV동물농장": "9.2", "KBS뉴스(12:00)": "9.2", "SBS8뉴스": "8.9", "숨터<재>": "8.3", "신비한TV서프라이즈": "8.0", "도전골든벨": "7.9", "TV쇼진품명품": "7.2", "잘먹고잘사는법식사하셨어요": "7.1"}, {"날짜": "20160307", "일일연속극(우리집꿀단지)": "27.0", "KBS9시뉴스": "18.7", "일일드라마(천상의약속)": "17.1", "창사특별기획(육룡이나르샤)": "16.1", "MBC아침드라마(내일도승리)": "14.8", "일일특별기획(아름다운당신)": "12.9", "월화특별기획(화려한유혹)": "12.7", "KBS뉴스7": "12.6", "가요무대": "11.6", "인간극장": "11.4", "아침일일연속극(내사위의여자)": "10.9", "일일드라마(마녀의성)": "10.5", "우리말겨루기": "10.1", "6시내고향": "10.1", "시청자칼럼우리사는세상": "10.0", "리얼스토리눈": "10.0", "KBS뉴스광장2부": "9.7", "생활의달인": "9.3", "아침마당": "9.2", "TV소설(내마음의꽃비)": "8.6"}, {"날짜": "20160308", "일일연속극(우리집꿀단지)": "27.5", "KBS9시뉴스": "19.3", "일일드라마(천상의약속)": "17.8", "창사특별기획(육룡이나르샤)": "16.1", "MBC아침드라마(내일도승리)": "14.2", "일일특별기획(아름다운당신)": "12.9", "월화특별기획(화려한유혹)": "12.7", "아침일일연속극(내사위의여자)": "11.2", "인간극장": "11.1", "일일드라마(마녀의성)": "10.5", "KBS뉴스7": "9.9", "이웃집찰스": "9.3", "6시내고향": "9.3", "아침마당": "9.2", "KBS뉴스광장2부": "9.0", "리얼스토리눈": "8.7", "시청자칼럼우리사는세상": "8.6", "KBS뉴스(09:30)": "8.4", "일일연속극(최고의연인)": "8.1", "TV소설(내마음의꽃비)": "8.0"}, {"날짜": "20160309", "공사창립특별기획(태양의후예)": "27.4", "일일연속극(우리집꿀단지)": "27.2", "KBS9시뉴스": "21.6", "일일드라마(천상의약속)": "15.8", "MBC아침드라마(내일도승리)": "14.4", "일일특별기획(아름다운당신)": "13.0", "KBS뉴스7": "11.8", "아침일일연속극(내사위의여자)": "11.7", "인간극장": "10.9", "사람과사람들": "10.4", "시청자칼럼우리사는세상": "9.7", "6시내고향": "9.6", "KBS뉴스광장2부": "9.4", "리얼스토리눈": "9.1", "아침마당": "9.1", "일일드라마(마녀의성)": "9.0", "TV소설(내마음의꽃비)": "8.7", "일일연속극(최고의연인)": "7.9", "영재발굴단": "7.8", "황금어장라디오스타": "7.8"}, {"날짜": "20160310", "공사창립특별기획(태양의후예)": "28.5", "일일연속극(우리집꿀단지)": "26.7", "KBS9시뉴스": "19.3", "일일드라마(천상의약속)": "15.8", "MBC아침드라마(내일도승리)": "14.0", "일일특별기획(아름다운당신)": "12.3", "순간포착": "11.9", "아침일일연속극(내사위의여자)": "11.1", "KBS뉴스7": "10.4", "일일드라마(마녀의성)": "10.3", "인간극장": "10.1", "아침마당": "9.8", "한국인의밥상": "9.4", "KBS뉴스광장2부": "9.2", "일일연속극(최고의연인)": "8.9", "6시내고향": "8.6", "TV소설(내마음의꽃비)": "8.2", "자기야": "8.1", "KBS뉴스(09:30)": "7.8", "리얼스토리눈": "7.8"}, {"날짜": "20160311", "일일연속극(우리집꿀단지)": "26.8", "KBS9시뉴스": "17.1", "일일드라마(천상의약속)": "16.9", "MBC아침드라마(내일도승리)": "15.4", "정글의법칙샵TONGA": "14.9", "일일특별기획(아름다운당신)": "11.4", "아침일일연속극(내사위의여자)": "11.3", "KBS뉴스7": "11.3", "인간극장": "10.7", "아침마당": "10.5", "6시내고향": "10.4", "궁금한이야기Y": "10.2", "일일드라마(마녀의성)": "10.0", "시청자칼럼우리사는세상": "10.0", "KBS뉴스광장2부": "9.2", "일일연속극(최고의연인)": "8.8", "TV소설(내마음의꽃비)": "8.8", "KBS뉴스(09:30)": "8.2", "나혼자산다": "8.1", "똑똑한소비자리포트": "7.5"}, {"날짜": "20160312", "주말연속극(아이가다섯)": "23.3", "주말특별기획(결혼계약)": "17.3", "KBS9시뉴스": "12.8", "주말드라마(가화만사성)": "12.7", "무한도전": "12.0", "불후의명곡": "11.8", "대하드라마(장영실)": "10.4", "시니어토크쇼황금연못": "10.3", "특별기획(미세스캅2)": "9.4", "KBS뉴스(09:30)": "9.3", "남북의창": "9.2", "걸어서세계속으로": "9.0", "그것이알고싶다": "8.7", "MBC뉴스데스크": "8.2", "KBS뉴스광장2부": "7.9", "인공지능의도전특별대국이세돌대알파고": "7.5", "KBS뉴스(19:00)": "7.5", "주말드라마(그래그런거야)": "7.5", "공사창립특별기획(태양의후예<재>)": "7.4", "휴먼다큐사람이좋다": "7.4"}, {"날짜": "20160313", "주말연속극(아이가다섯)": "27.2", "주말특별기획(결혼계약)": "17.8", "KBS9시뉴스": "15.6", "주말드라마(가화만사성)": "14.6", "전국노래자랑": "13.0", "대하드라마(장영실)": "12.0", "일밤(미스터리음악쇼복면가왕,리얼입대프로젝트진짜사나이2)": "11.7", "해피선데이": "11.7", "KBS뉴스(12:00)": "10.9", "TV동물농장": "10.2", "개그콘서트": "10.1", "인공지능의도전특별대국이세돌대알파고": "10.0", "SBS8뉴스": "10.0", "도전골든벨": "9.8", "주말드라마(그래그런거야)": "9.8", "숨터<재>": "9.6", "특별기획(미세스캅2)": "9.5", "일요일이좋다(런닝맨,서바이벌오디션K팝스타5)": "8.7", "MBC뉴스데스크": "8.6", "TV쇼진품명품": "8.3"}, {"날짜": "20160314", "일일연속극(우리집꿀단지)": "30.0", "KBS9시뉴스": "22.7", "일일드라마(천상의약속)": "18.4", "창사특별기획(육룡이나르샤)": "16.7", "MBC아침드라마(내일도승리)": "14.4", "일일특별기획(아름다운당신)": "13.2", "아침일일연속극(내사위의여자)": "11.8", "월화특별기획(화려한유혹)": "11.6", "가요무대": "11.5", "KBS뉴스7": "11.4", "우리말겨루기": "10.9", "인간극장": "10.5", "일일드라마(마녀의성)": "10.1", "6시내고향": "9.8", "시청자칼럼우리사는세상": "9.8", "KBS뉴스광장2부": "9.7", "리얼스토리눈": "9.6", "TV소설(내마음의꽃비)": "9.1", "일일연속극(최고의연인)": "9.0", "아침마당": "8.4"}, {"날짜": "20160315", "일일연속극(우리집꿀단지)": "29.4", "KBS9시뉴스": "20.7", "일일드라마(천상의약속)": "19.0", "창사특별기획(육룡이나르샤)": "16.2", "MBC아침드라마(내일도승리)": "14.7", "일일특별기획(아름다운당신)": "13.3", "월화특별기획(화려한유혹)": "12.7", "KBS뉴스7": "11.9", "일일드라마(마녀의성)": "11.2", "인간극장": "10.9", "아침일일연속극(내사위의여자)": "10.7", "6시내고향": "10.2", "KBS뉴스광장2부": "9.4", "리얼스토리눈": "9.1", "아침마당": "8.9", "일일연속극(최고의연인)": "8.9", "TV소설(내마음의꽃비)": "8.8", "이웃집찰스": "8.1", "인공지능의도전특별대국이세돌대알파고제5국": "7.8", "KBS뉴스(09:30)": "7.2"}, {"날짜": "20160316", "공사창립특별기획(태양의후예)": "28.3", "일일연속극(우리집꿀단지)": "27.4", "KBS9시뉴스": "20.4", "일일드라마(천상의약속)": "17.7", "MBC아침드라마(내일도승리)": "14.4", "일일특별기획(아름다운당신)": "12.8", "인간극장": "11.6", "아침일일연속극(내사위의여자)": "11.5", "일일드라마(마녀의성)": "10.7", "KBS뉴스7": "10.5", "아침마당": "9.7", "KBS뉴스광장2부": "9.5", "시청자칼럼우리사는세상": "9.0", "6시내고향": "8.7", "일일연속극(최고의연인)": "8.5", "사람과사람들": "8.5", "리얼스토리눈": "8.5", "TV소설(내마음의꽃비)": "8.5", "황금어장라디오스타": "8.2", "KBS뉴스(09:30)": "7.7"}, {"날짜": "20160317", "공사창립특별기획(태양의후예)": "28.8", "일일연속극(우리집꿀단지)": "27.5", "KBS9시뉴스": "17.6", "일일드라마(천상의약속)": "16.3", "MBC아침드라마(내일도승리)": "15.2", "일일특별기획(아름다운당신)": "12.6", "아침일일연속극(내사위의여자)": "11.3", "인간극장": "10.4", "일일드라마(마녀의성)": "10.3", "KBS뉴스광장2부": "9.5", "일일연속극(최고의연인)": "9.4", "KBS뉴스7": "9.3", "순간포착": "9.2", "한국인의밥상": "9.1", "TV소설(내마음의꽃비)": "8.9", "6시내고향": "8.3", "KBS스페셜(지리산벌꾼과담비)": "8.3", "리얼스토리눈": "8.1", "자기야": "7.8", "시청자칼럼우리사는세상": "7.6"}, {"날짜": "20160318", "일일연속극(우리집꿀단지)": "28.3", "KBS9시뉴스": "19.1", "일일드라마(천상의약속)": "17.6", "MBC아침드라마(내일도승리)": "15.0", "정글의법칙샵TONGA": "14.7", "일일특별기획(아름다운당신)": "12.7", "아침일일연속극(내사위의여자)": "11.4", "아침마당": "10.9", "6시내고향": "10.8", "시청자칼럼우리사는세상": "10.7", "KBS뉴스7": "10.4", "인간극장": "10.0", "일일드라마(마녀의성)": "9.7", "궁금한이야기Y": "9.7", "일일연속극(최고의연인)": "9.4", "나혼자산다": "9.3", "TV소설(내마음의꽃비)": "9.1", "KBS뉴스광장2부": "9.1", "KBS뉴스(09:30)": "8.2", "똑똑한소비자리포트": "7.4"}, {"날짜": "20160319", "주말연속극(아이가다섯)": "25.6", "주말특별기획(결혼계약)": "18.0", "주말드라마(가화만사성)": "15.1", "KBS9시뉴스": "12.5", "무한도전": "11.3", "대하드라마(장영실)": "10.4", "시니어토크쇼황금연못": "10.0", "불후의명곡": "9.3", "마이리틀텔레비전": "9.2", "특별기획(미세스캅2)": "9.1", "연예가중계": "8.4", "주말드라마(그래그런거야)": "8.4", "걸어서세계속으로": "8.3", "남북의창": "8.2", "그것이알고싶다": "8.0", "KBS뉴스(19:00)": "7.4", "KBS뉴스(09:30)": "7.4", "SBS8뉴스": "7.4", "KBS뉴스광장2부": "7.3", "토요일이좋다2부(백종원의3대천왕)": "7.2"}, {"날짜": "20160320", "주말연속극(아이가다섯)": "30.1", "주말특별기획(결혼계약)": "19.3", "주말드라마(가화만사성)": "14.9", "일밤1부(미스터리음악쇼복면가왕)": "13.2", "KBS9시뉴스": "12.8", "해피선데이": "12.5", "전국노래자랑": "12.2", "대하드라마(장영실)": "11.9", "일요일이좋다2부(서바이벌오디션K팝스타5)": "11.3", "일밤2부(리얼입대프로젝트진짜사나이2)": "11.2", "개그콘서트": "10.3", "TV동물농장": "10.1", "도전골든벨": "9.9", "주말드라마(그래그런거야)": "9.8", "KBS뉴스(12:00)": "9.5", "신비한TV서프라이즈": "8.7", "특별기획(미세스캅2)": "8.6", "잘먹고잘사는법식사하셨어요": "8.4", "숨터<재>": "8.2", "SBS8뉴스": "7.7"}, {"날짜": "20160321", "일일연속극(우리집꿀단지)": "28.6", "KBS9시뉴스": "20.7", "일일드라마(천상의약속)": "18.5", "창사특별기획(육룡이나르샤)": "16.2", "MBC아침드라마(내일도승리)": "13.7", "일일특별기획(아름다운당신)": "12.8", "아침일일연속극(내사위의여자)": "12.1", "월화특별기획(화려한유혹)": "11.9", "리얼스토리눈": "11.6", "가요무대": "11.4", "KBS뉴스7": "10.6", "일일드라마(마녀의성)": "10.6", "인간극장": "10.2", "KBS뉴스광장2부": "9.8", "6시내고향": "9.5", "일일연속극(최고의연인)": "9.2", "시청자칼럼우리사는세상": "9.0", "생활의달인": "8.6", "KBS뉴스라인": "8.5", "아침마당": "8.1"}, {"날짜": "20160322", "일일연속극(우리집꿀단지)": "27.0", "일일드라마(천상의약속)": "18.5", "KBS9시뉴스": "18.2", "창사특별기획(육룡이나르샤)": "17.3", "MBC아침드라마(내일도승리)": "14.9", "월화특별기획(화려한유혹)": "12.4", "일일특별기획(아름다운당신)": "12.3", "리얼스토리눈": "11.1", "아침일일연속극(내사위의여자)": "10.6", "KBS뉴스7": "10.6", "일일드라마(마녀의성)": "10.2", "KBS뉴스광장2부": "9.8", "일일연속극(최고의연인)": "9.4", "아침마당": "9.3", "6시내고향": "9.2", "인간극장": "9.2", "TV소설(내마음의꽃비)": "8.9", "시청자칼럼우리사는세상": "8.4", "KBS뉴스(09:30)": "7.6"}, {"날짜": "20160323", "공사창립특별기획(태양의후예)": "30.4", "일일연속극(우리집꿀단지)": "27.7", "KBS9시뉴스": "21.2", "일일드라마(천상의약속)": "17.8", "MBC아침드라마(내일도승리)": "14.2", "일일특별기획(아름다운당신)": "13.1", "아침일일연속극(내사위의여자)": "11.5", "일일드라마(마녀의성)": "11.1", "리얼스토리눈": "10.5", "KBS뉴스7": "10.0", "KBS뉴스광장2부": "9.9", "아침마당": "8.9", "6시내고향": "8.8", "인간극장": "8.7", "일일연속극(최고의연인)": "8.4", "시청자칼럼우리사는세상": "8.0", "TV소설(내마음의꽃비)": "7.4", "사람과사람들": "7.1", "생로병사의비밀": "7.1", "황금어장라디오스타": "7.0"}, {"날짜": "20160324", "공사창립특별기획(태양의후예)": "31.6", "일일연속극(우리집꿀단지)": "27.8", "KBS9시뉴스": "17.2", "일일드라마(천상의약속)": "17.0", "MBC아침드라마(내일도승리)": "15.7", "일일특별기획(아름다운당신)": "12.5", "아침일일연속극(내사위의여자)": "11.0", "일일연속극(최고의연인)": "10.9", "KBS뉴스7": "10.1", "SBS스포츠축구(월드컵아시아예선한국:레바논)": "9.9", "시청자칼럼우리사는세상": "9.8", "인간극장": "9.7", "KBS뉴스광장2부": "9.6", "한국인의밥상": "9.5", "아침마당": "9.1", "6시내고향": "8.8", "리얼스토리눈": "8.5", "자기야": "8.3", "TV소설(내마음의꽃비)": "8.2", "KBS뉴스(09:30)": "7.9"}, {"날짜": "20160325", "일일연속극(우리집꿀단지)": "26.2", "KBS9시뉴스": "17.6", "일일드라마(천상의약속)": "16.9", "MBC아침드라마(내일도승리)": "15.5", "정글의법칙샵TONGA": "13.0", "아침일일연속극(내사위의여자)": "11.3", "일일드라마(마녀의성)": "10.8", "궁금한이야기Y": "10.7", "KBS뉴스7": "10.3", "KBS뉴스광장2부": "9.9", "시청자칼럼우리사는세상": "9.7", "6시내고향": "9.7", "인간극장": "9.4", "아침마당": "8.5", "나혼자산다": "8.4", "일일연속극(최고의연인)": "8.2", "TV소설(내마음의꽃비)": "7.7", "똑똑한소비자리포트": "7.4", "SBS8뉴스": "7.3", "KBS뉴스광장1부": "6.7"}, {"날짜": "20160326", "주말연속극(아이가다섯)": "23.2", "주말특별기획(결혼계약)": "18.4", "주말드라마(가화만사성)": "13.3", "KBS9시뉴스": "12.6", "무한도전": "11.5", "불후의명곡": "10.9", "대하드라마(장영실)": "10.2", "다큐공감": "9.8", "공사창립특별기획(태양의후예<재>)": "9.6", "시니어토크쇼황금연못": "9.0", "그것이알고싶다": "8.3", "주말드라마(그래그런거야)": "8.1", "연예가중계": "7.8", "마이리틀텔레비전": "7.7", "KBS뉴스광장2부": "7.6", "특별기획(미세스캅2)": "7.6", "MBC뉴스데스크": "7.4", "토요일이좋다2부(백종원의3대천왕)": "7.3", "남북의창": "7.3", "SBS8뉴스": "7.1"}, {"날짜": "20160327", "주말연속극(아이가다섯)": "28.2", "주말특별기획(결혼계약)": "20.4", "일밤1부(미스터리음악쇼복면가왕)": "15.8", "주말드라마(가화만사성)": "14.4", "해피선데이": "14.1", "KBS9시뉴스": "13.0", "일요일이좋다2부(서바이벌오디션K팝스타5)": "11.5", "전국노래자랑": "11.4", "KBS스포츠축구(국가대표팀친선경기한국:태국)": "10.4", "주말드라마(그래그런거야)": "10.1", "TV동물농장": "10.0", "특별기획(미세스캅2)": "9.6", "도전골든벨": "9.4", "KBS뉴스(12:00)": "9.3", "일밤2부(리얼입대프로젝트진짜사나이2)": "9.3", "SBS8뉴스": "8.8", "숨터<재>": "8.6", "잘먹고잘사는법식사하셨어요": "7.9", "신비한TV서프라이즈": "7.8", "TV쇼진품명품": "7.5"}, {"날짜": "20160328", "일일연속극(우리집꿀단지)": "27.2", "KBS9시뉴스": "21.1", "일일드라마(천상의약속)": "17.0", "MBC아침드라마(내일도승리)": "15.3", "일일특별기획(아름다운당신)": "14.6", "가요무대": "12.9", "월화드라마(대박)": "11.8", "인간극장": "11.4", "아침일일연속극(내사위의여자)": "11.2", "리얼스토리눈": "10.8", "KBS뉴스7": "10.5", "일일연속극(최고의연인)": "10.3", "월화드라마(동네변호사조들호)": "10.1", "시청자칼럼우리사는세상": "9.6", "KBS뉴스광장2부": "9.6", "우리말겨루기": "9.1", "6시내고향": "9.0", "아침마당": "9.0", "MBC뉴스데스크": "8.1", "KBS뉴스라인": "7.7"}, {"날짜": "20160329", "일일연속극(우리집꿀단지)": "28.0", "일일드라마(천상의약속)": "19.8", "KBS9시뉴스": "19.7", "MBC아침드라마(내일도승리)": "15.7", "일일특별기획(아름다운당신)": "13.1", "월화드라마(대박)": "12.2", "아침일일연속극(내사위의여자)": "11.6", "월화드라마(동네변호사조들호)": "11.4", "일일드라마(마녀의성)": "10.4", "인간극장": "9.7", "리얼스토리눈": "9.6", "일일연속극(최고의연인)": "9.2", "아침마당": "9.1", "이웃집찰스": "8.9", "KBS뉴스광장2부": "8.4", "KBS뉴스(09:30)": "8.2", "2TV생생정보": "8.2", "TV소설(내마음의꽃비)": "8.1", "KBS뉴스7": "7.6", "월화특별기획(몬스터)": "7.0"}, {"날짜": "20160330", "공사창립특별기획(태양의후예)": "31.9", "일일연속극(우리집꿀단지)": "27.3", "KBS9시뉴스": "23.3", "일일드라마(천상의약속)": "19.1", "MBC아침드라마(내일도승리)": "16.1", "일일특별기획(아름다운당신)": "12.6", "아침일일연속극(내사위의여자)": "11.8", "인간극장": "10.9", "일일드라마(마녀의성)": "10.9", "KBS뉴스7": "10.7", "아침마당": "9.6", "리얼스토리눈": "9.2", "황금어장라디오스타": "9.2", "사람과사람들": "9.1", "일일연속극(최고의연인)": "9.1", "KBS뉴스광장2부": "8.9", "6시내고향": "8.8", "시청자칼럼우리사는세상": "7.6", "TV소설(내마음의꽃비)": "7.3", "KBS뉴스(09:30)": "7.1"}, {"날짜": "20160331", "공사창립특별기획(태양의후예)": "33.0", "일일연속극(우리집꿀단지)": "27.1", "일일드라마(천상의약속)": "17.8", "KBS9시뉴스": "17.7", "MBC아침드라마(내일도승리)": "15.5", "아침일일연속극(내사위의여자)": "11.9", "일일특별기획(아름다운당신)": "11.4", "일일드라마(마녀의성)": "10.9", "KBS뉴스7": "10.5", "인간극장": "10.1", "한국인의밥상": "9.8", "순간포착": "9.5", "KBS뉴스광장2부": "9.1", "시청자칼럼우리사는세상": "8.7", "6시내고향": "8.5", "일일연속극(최고의연인)": "8.4", "리얼스토리눈": "8.4", "TV소설(내마음의꽃비)": "7.8", "자기야": "7.8", "해피투게더": "7.1"}]